{"importBase":"import","nativeBase":"native","name":"app","deps":["main"],"uuids":["01LG242qVFhrcD0s1SZtzk","02KrJfSNVIk5PzUXS7+OKZ","0cmHt2/XVKAKMGDfG+/CAI","18e+Exx+5Iz4Osn/aWh1mS","189ko6RKtOvYUUtDLXWeOa","1aY5DXxPJHaLPLLjfis3Nq","22NuJnBtdMdIoZONUf/NqM","24VTUihnxGH6Y7w2wulCpb","25GdXOVWtOUI1/8CHuN1WJ","29buUTPChCbqAUA3xHPk9X","2cQKhnpABI06g/ghem1TFs","2cUdZD3h9HvrnOlrnZybMk","2clQyNo5xGtLigYnaNCqXq","31hKEwHXVG+Yeiu6kJ0vFh","349lWTarJCCL+/HgrL/JrX","40WqCHNHVHApzVU75bkwdG","41eWW/UC5EuLNbS3S/KZ6M","47VQpPjthO17rQ5weN6dGL","50jzlqDmtEAKkP+wnZ43rg","60ns/9xS5Av4UuFmXUIAf1","62rca7phpF5Y8u4kPnsOCP","7506U/Ug1HrZij+PB3tOMf","7bt/2tbMtFH6VQiBwZxfdE","7dj5uJT9FMn6OrOOx83tfK","80kjtrHiZIVaddqhEuXqdO","85pc/NTK1LqrXDy7bUgZOV","8fFcYQU4hB8ppV5D+EtTNs","90I85PxydPKogtGpK0hp24","93Osu2g7ZHyIzoKJD8H8Qr","9cHjHTgl9L7b9efIJVcz7Z","9fKCJYqu5MTrB0RmKWrXeb","a2gj6aN+1Keben1GKi5s1Z","a2sHPfTeJAD7ZpFwJ+9+3i","aaVX297qdKMKFgEKcrTeq6","c2C5/UR+9BEZJ1LU3ZBuhI","c6GL2f9mRMX6KF7iyhJyr8","d6e1eFbkFJGYGf3b6IIiwF","dbWxXKzgxLm7vZMWIZF+YM","e0g0jL9ENCsI0/IfzBiNqv","e0lj2msoRLvqAnD21DeisR","eaZ/48PrtFBrAlPpaG7zXm","efxt+/iZ5JF49dHx4U1cGs","f7YpoNRHVIoK8JNGc4dEUc","fc89K+i+1McbaHY8VU2WMv","01LG242qVFhrcD0s1SZtzk@6c48a","01LG242qVFhrcD0s1SZtzk@f9941","01b9a57a9","01e68b892","02KrJfSNVIk5PzUXS7+OKZ@6c48a","02KrJfSNVIk5PzUXS7+OKZ@f9941","05c3fdd49","0bdo2+jAVOQa4/OjJ7GYyJ","0cmHt2/XVKAKMGDfG+/CAI@6c48a","0cmHt2/XVKAKMGDfG+/CAI@f9941","0d352e9f7","12Pn5THYlOhJySer1dAE82","13v2Bm6UpHnqg9mOyDSvPG","18e+Exx+5Iz4Osn/aWh1mS@6c48a","18e+Exx+5Iz4Osn/aWh1mS@f9941","189ko6RKtOvYUUtDLXWeOa@6c48a","189ko6RKtOvYUUtDLXWeOa@f9941","1aY5DXxPJHaLPLLjfis3Nq@6c48a","1aY5DXxPJHaLPLLjfis3Nq@f9941","20g1ukYUVPvKWKBRznAKo+@f9941","22NuJnBtdMdIoZONUf/NqM@6c48a","22NuJnBtdMdIoZONUf/NqM@f9941","24VTUihnxGH6Y7w2wulCpb@6c48a","24VTUihnxGH6Y7w2wulCpb@f9941","25GdXOVWtOUI1/8CHuN1WJ@6c48a","25GdXOVWtOUI1/8CHuN1WJ@f9941","29buUTPChCbqAUA3xHPk9X@6c48a","29buUTPChCbqAUA3xHPk9X@f9941","2cQKhnpABI06g/ghem1TFs@6c48a","2cQKhnpABI06g/ghem1TFs@f9941","2cUdZD3h9HvrnOlrnZybMk@6c48a","2cUdZD3h9HvrnOlrnZybMk@f9941","2clQyNo5xGtLigYnaNCqXq@6c48a","2clQyNo5xGtLigYnaNCqXq@f9941","31hKEwHXVG+Yeiu6kJ0vFh@6c48a","31hKEwHXVG+Yeiu6kJ0vFh@f9941","349lWTarJCCL+/HgrL/JrX@6c48a","349lWTarJCCL+/HgrL/JrX@f9941","37cGggVuFLOKl0v3PK5Au+","38AwUBov9KpKWxaqrinl+x","3eslkQ229KZ4coGZ9Uaznh","41eWW/UC5EuLNbS3S/KZ6M@6c48a","41eWW/UC5EuLNbS3S/KZ6M@f9941","44GqluBKdKFLsPXaREBPft","472OHzxWpC8olO8IxH3B9M","50jzlqDmtEAKkP+wnZ43rg@6c48a","50jzlqDmtEAKkP+wnZ43rg@f9941","54TknWPwVPqJqeCR+Y/Czo@f9941","5bpPL+FcJJmpX+m534dDyV","60ns/9xS5Av4UuFmXUIAf1@6c48a","60ns/9xS5Av4UuFmXUIAf1@f9941","62rca7phpF5Y8u4kPnsOCP@6c48a","62rca7phpF5Y8u4kPnsOCP@f9941","64lOAYvfdNf7B42rrN42St","6eDCEEivBI7YuGAyXBev/m","72TaiVaGRHZ5DQbqV19wm7","7506U/Ug1HrZij+PB3tOMf@6c48a","7506U/Ug1HrZij+PB3tOMf@f9941","7bt/2tbMtFH6VQiBwZxfdE@6c48a","7bt/2tbMtFH6VQiBwZxfdE@f9941","7dj5uJT9FMn6OrOOx83tfK@6c48a","7dj5uJT9FMn6OrOOx83tfK@f9941","81wctsrphKCoYkV8wNV34C","85pc/NTK1LqrXDy7bUgZOV@6c48a","85pc/NTK1LqrXDy7bUgZOV@f9941","8aYG84AjVJ3Z0KkWNObQNZ","8fFcYQU4hB8ppV5D+EtTNs@6c48a","8fFcYQU4hB8ppV5D+EtTNs@f9941","90I85PxydPKogtGpK0hp24@6c48a","90I85PxydPKogtGpK0hp24@f9941","91TZnGbZ1EGbp8nUS0rBf4","93Osu2g7ZHyIzoKJD8H8Qr@6c48a","93Osu2g7ZHyIzoKJD8H8Qr@f9941","95EkngnxZFbYuFpsqVTaFr@f9941","9cHjHTgl9L7b9efIJVcz7Z@6c48a","9cHjHTgl9L7b9efIJVcz7Z@f9941","9fKCJYqu5MTrB0RmKWrXeb@6c48a","9fKCJYqu5MTrB0RmKWrXeb@f9941","a2gj6aN+1Keben1GKi5s1Z@6c48a","a2gj6aN+1Keben1GKi5s1Z@f9941","a2sHPfTeJAD7ZpFwJ+9+3i@6c48a","a2sHPfTeJAD7ZpFwJ+9+3i@f9941","aaVX297qdKMKFgEKcrTeq6@6c48a","aaVX297qdKMKFgEKcrTeq6@f9941","afxHkx8GZGsJC+n+YfITQo@f9941","b7MFJ8MjNBwqr3fNq1j5dJ@f9941","b9GoaqhetAoLub1rk7BMmk","bbUA3YVjFE6ZtdGUTNVKIZ@f9941","bbzZo6vMZKYoyrzl1Uanp1","bcVtufzNpAErzfPSgY/3F9@f9941","c2C5/UR+9BEZJ1LU3ZBuhI@6c48a","c2C5/UR+9BEZJ1LU3ZBuhI@f9941","c6GL2f9mRMX6KF7iyhJyr8@6c48a","c6GL2f9mRMX6KF7iyhJyr8@f9941","caS0c8H1NJGqlWDOu+Eeg/","d6e1eFbkFJGYGf3b6IIiwF@6c48a","d6e1eFbkFJGYGf3b6IIiwF@f9941","deEV5APuFI0YkehHmewgEG","e0g0jL9ENCsI0/IfzBiNqv@6c48a","e0g0jL9ENCsI0/IfzBiNqv@f9941","e0lj2msoRLvqAnD21DeisR@6c48a","e0lj2msoRLvqAnD21DeisR@f9941","e1E8zWHY9NurHsZ8aX68Ml","e1e0UmV6JI06zJzwnzCqE4","e2ZoZ9+QNAgI/sy5ucJoGt","eaZ/48PrtFBrAlPpaG7zXm@6c48a","eaZ/48PrtFBrAlPpaG7zXm@f9941","efxt+/iZ5JF49dHx4U1cGs@6c48a","efxt+/iZ5JF49dHx4U1cGs@f9941","f1eztQUd1HcY07rpa1Ucum","f7YpoNRHVIoK8JNGc4dEUc@6c48a","f7YpoNRHVIoK8JNGc4dEUc@f9941","fc89K+i+1McbaHY8VU2WMv@6c48a","fc89K+i+1McbaHY8VU2WMv@f9941","ffuIqPr2JI9I8dPLYGRDpD@f9941"],"paths":{"15":["HomeView",0],"37":["AppRes",0]},"scenes":{},"packs":{"01b9a57a9":["49","51","55","65","67","71","75","77","82","83","84","86","87","88","90","92","96","97","99","101","105","24","106","108","109","113","114","116","123","125","127","130","132","135","138","140","37","141","146","148","153"],"01e68b892":["45","53","56","58","60","62","69","73","79","81","15","17","94","98","103","111","119","121","137","143","145","150","152","155","157"],"05c3fdd49":["52","61","72","74","76","102","104","110","118","120","44","59","48","80","95","100","107","57","70","89","93","115","64","68","78","112","85","66","124","122","126","134","136","139","144","142","149","151","154","156"],"0d352e9f7":["2","5","10","11","12","22","23","26","29","30","0","4","1","14","20","21","25","3","9","18","19","28","6","8","13","27","16","7","32","31","33","34","35","36","39","38","40","41","42","43"]},"versions":{"import":[46,"e3832",47,"d8d47",50,"5f9db",54,"55ef5"],"native":[0,"3d660",1,"668a0",2,"f1b07",3,"bae98",4,"581e6",5,"2a524",6,"3f897",7,"db19b",8,"43572",9,"84fe0",10,"4d027",11,"3e595",12,"1813f",13,"cd72e",14,"9c487",16,"39777",17,"155a1",18,"82b74",19,"92599",20,"b5f77",21,"e3696",22,"743b4",23,"cea68",25,"5d63c",26,"f44f9",27,"eb295",28,"48b21",29,"e10d7",30,"90c23",31,"899f9",32,"64d1d",33,"d3437",34,"6ad3b",35,"2381a",36,"edae5",38,"13b43",39,"4e6b9",40,"6e2c6",41,"0868e",42,"4d4ef",43,"f2acb",24,"8d33b"]},"redirect":[63,"0",91,"0",117,"0",128,"0",129,"0",131,"0",133,"0",147,"0",158,"0"],"debug":false,"extensionMap":{},"hasPreloadScript":true,"types":["cc.Prefab"]}